Workbook
Name Slicer_Action_Recommendation: #N/A
Name Slicer_Alert_Status: #N/A
Name Slicer_Batch_ID: #N/A
Name Slicer_Category: #N/A
Name Slicer_Expiry_Alert_30Days1: #N/A
Name Slicer_Product_Name: #N/A

Sheet DASHBOARD
A1: PT AURA NUSANTARA COSMETICS | H1: =MASTER_DATA!O326 -> 4210550000 | N1: =MASTER_DATA!P326 -> 776450000 | T1: =MASTER_DATA!I326 -> 77850 | Z1: =(COUNTIF(MASTER_DATA!Q6:Q325, "EXPIRED") + COUNTIF(MASTER_DATA!Q6:Q325, "CRITICAL"))/(COUNTIF(MASTER_DATA!Q6:Q325, "EXPIRED") + COUNTIF(MASTER_DATA!Q6:Q325, "CRITICAL")+COUNTIF(MASTER_DATA!Q6:Q325, "SAFE")+COUNTIF(MASTER_DATA!Q6:Q325, "WARNING"))*100 -> 18.75 | AF1: =AVERAGE(MASTER_DATA!M6:M325) -> 203.15938 | AL1: =COUNTIF(Analysis_FEFO!J5:J174, "Compliant") / COUNTA(Analysis_FEFO!J5:J174) -> 0.094117647
H8: TOTAL INVENTORY VALUE | N8: TOTAL RISK VALUATION | T8: TOTAL STOCK REMAINING | Z8: CRITICAL & EXPIRED BATCHES (%) | AF8: AVERAGE DAYS TO EXPIRY | AL8: FEFO COMPLIANCE RATE
A9: FEFO & Inventory Risk Management Dashboard
A100: CREATED BY NUR LAILA KAMALIYAH

Sheet MASTER_DATA
A1: PT AURA NUSANTARA COSMETICS
A3: Dataset used: Dummy/Simulated Inventory & Shipment Data (for portfolio illustration purposes)
A5: Batch_ID | B5: SKU_Code | C5: Product_Name | D5: Category | E5: Inbound_Date | F5: Expiry_Date | G5: Qty_Inbound | H5: Qty_Outbound | I5: Qty_Remaining | J5: Unit_Cost | K5: Total_Inbound_Value | L5: Total_COGS_Outbound | M5: Days_To_Expiry | N5: Expiry_Alert_30Days | O5: Ending_Inventory_Value | P5: Risk_Valuation | Q5: Alert_Status | R5: Action_Recommendation
A6: B2026-1001 | B6: SK-RET-07 | C6: Retinol Night Cream 30g | D6: Moisturizer | E6: 46079 | F6: 46452 | G6: 300 | H6: =SUMIF(Analysis_FEFO!$E$5:$E$174, A6, Analysis_FEFO!$G$5:$G$174) -> 0 | I6: =G6-H6 -> 300 | J6: 84000 | K6: =G6*J6 -> 25200000 | L6: =H6*J6 -> 0 | M6: =F6-TODAY() -> 130 | N6: =IF(M6<=0, "EXPIRED", IF(M6<=30, "EXPIRING SOON (<30 DAYS)", "SAFE")) -> SAFE | O6: =I6*J6 -> 25200000 | P6: =IF(OR(Q6="CRITICAL", Q6="EXPIRED"), O6, 0) -> 0 | Q6: =IF(M6<0, "EXPIRED", IF(M6<=60, "CRITICAL", IF(M6<=180, "WARNING", "SAFE"))) -> WARNING | R6: {=_xlfn.IFS(Q6="EXPIRED", "WRITE-OFF", Q6="WARNING", "FlASH SALE ", Q6="CRITICAL", "FEFO PRIORITY", Q6="SAFE", "REGULAR SALES")} -> FlASH SALE
A7: B2026-1002 | B7: CL-C20-03 | C7: Vitamin C Cleanser 100ml | D7: Cleanser | E7: 46023 | F7: 46546 | G7: 250 | H7: =SUMIF(Analysis_FEFO!$E$5:$E$174, A7, Analysis_FEFO!$G$5:$G$174) -> 0 | I7: =G7-H7 -> 250 | J7: 34000 | K7: =G7*J7 -> 8500000 | L7: =H7*J7 -> 0 | M7: =F7-TODAY() -> 224 | N7: =IF(M7<=0, "EXPIRED", IF(M7<=30, "EXPIRING SOON (<30 DAYS)", "SAFE")) -> SAFE | O7: =I7*J7 -> 8500000 | P7: =IF(OR(Q7="CRITICAL", Q7="EXPIRED"), O7, 0) -> 0 | Q7: =IF(M7<0, "EXPIRED", IF(M7<=60, "CRITICAL", IF(M7<=180, "WARNING", "SAFE"))) -> SAFE | R7: {=_xlfn.IFS(Q7="EXPIRED", "WRITE-OFF", Q7="WARNING", "FlASH SALE ", Q7="CRITICAL", "FEFO PRIORITY", Q7="SAFE", "REGULAR SALES")} -> REGULAR SALES
A8: B2026-1003 | B8: MK-LIP-06 | C8: Velvet Lip Tint 4g | D8: Makeup | E8: 46066 | F8: 46440 | G8: 200 | H8: =SUMIF(Analysis_FEFO!$E$5:$E$174, A8, Analysis_FEFO!$G$5:$G$174) -> 0 | I8: =G8-H8 -> 200 | J8: 35000 | K8: =G8*J8 -> 7000000 | L8: =H8*J8 -> 0 | M8: =F8-TODAY() -> 118 | N8: =IF(M8<=0, "EXPIRED", IF(M8<=30, "EXPIRING SOON (<30 DAYS)", "SAFE")) -> SAFE | O8: =I8*J8 -> 7000000 | P8: =IF(OR(Q8="CRITICAL", Q8="EXPIRED"), O8, 0) -> 0 | Q8: =IF(M8<0, "EXPIRED", IF(M8<=60, "CRITICAL", IF(M8<=180, "WARNING", "SAFE"))) -> WARNING | R8: {=_xlfn.IFS(Q8="EXPIRED", "WRITE-OFF", Q8="WARNING", "FlASH SALE ", Q8="CRITICAL", "FEFO PRIORITY", Q8="SAFE", "REGULAR SALES")} -> FlASH SALE
A9: B2026-1004 | B9: MO-HYA-05 | C9: Hyaluronic Acid Moisturizer 50g | D9: Moisturizer | E9: 45969 | F9: 46245 | G9: 100 | H9: =SUMIF(Analysis_FEFO!$E$5:$E$174, A9, Analysis_FEFO!$G$5:$G$174) -> 0 | I9: =G9-H9 -> 100 | J9: 68000 | K9: =G9*J9 -> 6800000 | L9: =H9*J9 -> 0 | M9: =F9-TODAY() -> -77 | N9: =IF(M9<=0, "EXPIRED", IF(M9<=30, "EXPIRING SOON (<30 DAYS)", "SAFE")) -> EXPIRED | O9: =I9*J9 -> 6800000 | P9: =IF(OR(Q9="CRITICAL", Q9="EXPIRED"), O9, 0) -> 6800000 | Q9: =IF(M9<0, "EXPIRED", IF(M9<=60, "CRITICAL", IF(M9<=180, "WARNING", "SAFE"))) -> EXPIRED | R9: {=_xlfn.IFS(Q9="EXPIRED", "WRITE-OFF", Q9="WARNING", "FlASH SALE ", Q9="CRITICAL", "FEFO PRIORITY", Q9="SAFE", "REGULAR SALES")} -> WRITE-OFF
A10: B2026-1005 | B10: SK-NNC-01 | C10: Niacinamide Serum 30ml | D10: Serum | E10: 45867 | F10: 46514 | G10: 1000 | H10: =SUMIF(Analysis_FEFO!$E$5:$E$174, A10, Analysis_FEFO!$G$5:$G$174) -> 0 | I10: =G10-H10 -> 1000 | J10: 51000 | K10: =G10*J10 -> 51000000 | L10: =H10*J10 -> 0 | M10: =F10-TODAY() -> 192 | N10: =IF(M10<=0, "EXPIRED", IF(M10<=30, "EXPIRING SOON (<30 DAYS)", "SAFE")) -> SAFE | O10: =I10*J10 -> 51000000 | P10: =IF(OR(Q10="CRITICAL", Q10="EXPIRED"), O10, 0) -> 0 | Q10: =IF(M10<0, "EXPIRED", IF(M10<=60, "CRITICAL", IF(M10<=180, "WARNING", "SAFE"))) -> SAFE | R10: {=_xlfn.IFS(Q10="EXPIRED", "WRITE-OFF", Q10="WARNING", "FlASH SALE ", Q10="CRITICAL", "FEFO PRIORITY", Q10="SAFE", "REGULAR SALES")} -> REGULAR SALES
A11: B2026-1006 | B11: CL-C20-03 | C11: Vitamin C Cleanser 100ml | D11: Cleanser | E11: 45863 | F11: 46592 | G11: 100 | H11: =SUMIF(Analysis_FEFO!$E$5:$E$174, A11, Analysis_FEFO!$G$5:$G$174) -> 0 | I11: =G11-H11 -> 100 | J11: 34000 | K11: =G11*J11 -> 3400000 | L11: =H11*J11 -> 0 | M11: =F11-TODAY() -> 270 | N11: =IF(M11<=0, "EXPIRED", IF(M11<=30, "EXPIRING SOON (<30 DAYS)", "SAFE")) -> SAFE | O11: =I11*J11 -> 3400000 | P11: =IF(OR(Q11="CRITICAL", Q11="EXPIRED"), O11, 0) -> 0 | Q11: =IF(M11<0, "EXPIRED", IF(M11<=60, "CRITICAL", IF(M11<=180, "WARNING", "SAFE"))) -> SAFE | R11: {=_xlfn.IFS(Q11="EXPIRED", "WRITE-OFF", Q11="WARNING", "FlASH SALE ", Q11="CRITICAL", "FEFO PRIORITY", Q11="SAFE", "REGULAR SALES")} -> REGULAR SALES
A12: B2026-1007 | B12: SK-RET-07 | C12: Retinol Night Cream 30g | D12: Moisturizer | E12: 45829 | F12: 46466 | G12: 750 | H12: =SUMIF(Analysis_FEFO!$E$5:$E$174, A12, Analysis_FEFO!$G$5:$G$174) -> 750 | I12: =G12-H12 -> 0 | J12: 86000 | K12: =G12*J12 -> 64500000 | L12: =H12*J12 -> 64500000 | M12: =F12-TODAY() -> 144 | N12: =IF(M12<=0, "EXPIRED", IF(M12<=30, "EXPIRING SOON (<30 DAYS)", "SAFE")) -> SAFE | O12: =I12*J12 -> 0 | P12: =IF(OR(Q12="CRITICAL", Q12="EXPIRED"), O12, 0) -> 0 | Q12: =IF(M12<0, "EXPIRED", IF(M12<=60, "CRITICAL", IF(M12<=180, "WARNING", "SAFE"))) -> WARNING | R12: {=_xlfn.IFS(Q12="EXPIRED", "WRITE-OFF", Q12="WARNING", "FlASH SALE ", Q12="CRITICAL", "FEFO PRIORITY", Q12="SAFE", "REGULAR SALES")} -> FlASH SALE
A13: B2026-1008 | B13: SK-SUN-02 | C13: Sunscreen SPF 50 PA+++ | D13: Sunscreen | E13: 46073 | F13: 46514 | G13: 300 | H13: =SUMIF(Analysis_FEFO!$E$5:$E$174, A13, Analysis_FEFO!$G$5:$G$174) -> 300 | I13: =G13-H13 -> 0 | J13: 61000 | K13: =G13*J13 -> 18300000 | L13: =H13*J13 -> 18300000 | M13: =F13-TODAY() -> 192 | N13: =IF(M13<=0, "EXPIRED", IF(M13<=30, "EXPIRING SOON (<30 DAYS)", "SAFE")) -> SAFE | O13: =I13*J13 -> 0 | P13: =IF(OR(Q13="CRITICAL", Q13="EXPIRED"), O13, 0) -> 0 | Q13: =IF(M13<0, "EXPIRED", IF(M13<=60, "CRITICAL", IF(M13<=180, "WARNING", "SAFE"))) -> SAFE | R13: {=_xlfn.IFS(Q13="EXPIRED", "WRITE-OFF", Q13="WARNING", "FlASH SALE ", Q13="CRITICAL", "FEFO PRIORITY", Q13="SAFE", "REGULAR SALES")} -> REGULAR SALES
A14: B2026-1009 | B14: CL-MCL-08 | C14: Micellar Water Cleanse 250ml | D14: Cleanser | E14: 45843 | F14: 46551 | G14: 200 | H14: =SUMIF(Analysis_FEFO!$E$5:$E$174, A14, Analysis_FEFO!$G$5:$G$174) -> 0 | I14: =G14-H14 -> 200 | J14: 28000 | K14: =G14*J14 -> 5600000 | L14: =H14*J14 -> 0 | M14: =F14-TODAY() -> 229 | N14: =IF(M14<=0, "EXPIRED", IF(M14<=30, "EXPIRING SOON (<30 DAYS)", "SAFE")) -> SAFE | O14: =I14*J14 -> 5600000 | P14: =IF(OR(Q14="CRITICAL", Q14="EXPIRED"), O14, 0) -> 0 | Q14: =IF(M14<0, "EXPIRED", IF(M14<=60, "CRITICAL", IF(M14<=180, "WARNING", "SAFE"))) -> SAFE | R14: {=_xlfn.IFS(Q14="EXPIRED", "WRITE-OFF", Q14="WARNING", "FlASH SALE ", Q14="CRITICAL", "FEFO PRIORITY", Q14="SAFE", "REGULAR SALES")} -> REGULAR SALES
A15: B2026-1010 | B15: SK-SUN-02 | C15: Sunscreen SPF 50 PA+++ | D15: Sunscreen | E15: 45862 | F15: 46593 | G15: 100 | H15: =SUMIF(Analysis_FEFO!$E$5:$E$174, A15, Analysis_FEFO!$G$5:$G$174) -> 0 | I15: =G15-H15 -> 100 | J15: 56000 | K15: =G15*J15 -> 5600000 | L15: =H15*J15 -> 0 | M15: =F15-TODAY() -> 271 | N15: =IF(M15<=0, "EXPIRED", IF(M15<=30, "EXPIRING SOON (<30 DAYS)", "SAFE")) -> SAFE | O15: =I15*J15 -> 5600000 | P15: =IF(OR(Q15="CRITICAL", Q15="EXPIRED"), O15, 0) -> 0 | Q15: =IF(M15<0, "EXPIRED", IF(M15<=60, "CRITICAL", IF(M15<=180, "WARNING", "SAFE"))) -> SAFE | R15: {=_xlfn.IFS(Q15="EXPIRED", "WRITE-OFF", Q15="WARNING", "FlASH SALE ", Q15="CRITICAL", "FEFO PRIORITY", Q15="SAFE", "REGULAR SALES")} -> REGULAR SALES
A16: B2026-1011 | B16: TN-CEN-10 | C16: Centella Asiatica Soothing Essence | D16: Toner | E16: 45852 | F16: 46586 | G16: 750 | H16: =SUMIF(Analysis_FEFO!$E$5:$E$174, A16, Analysis_FEFO!$G$5:$G$174) -> 0 | I16: =G16-H16 -> 750 | J16: 59000 | K16: =G16*J16 -> 44250000 | L16: =H16*J16 -> 0 | M16: =F16-TODAY() -> 264 | N16: =IF(M16<=0, "EXPIRED", IF(M16<=30, "EXPIRING SOON (<30 DAYS)", "SAFE")) -> SAFE | O16: =I16*J16 -> 44250000 | P16: =IF(OR(Q16="CRITICAL", Q16="EXPIRED"), O16, 0) -> 0 | Q16: =IF(M16<0, "EXPIRED", IF(M16<=60, "CRITICAL", IF(M16<=180, "WARNING", "SAFE"))) -> SAFE | R16: {=_xlfn.IFS(Q16="EXPIRED", "WRITE-OFF", Q16="WARNING", "FlASH SALE ", Q16="CRITICAL", "FEFO PRIORITY", Q16="SAFE", "REGULAR SALES")} -> REGULAR SALES
A17: B2026-1012 | B17: SK-RET-07 | C17: Retinol Night Cream 30g | D17: Moisturizer | E17: 46060 | F17: 46507 | G17: 500 | H17: =SUMIF(Analysis_FEFO!$E$5:$E$174, A17, Analysis_FEFO!$G$5:$G$174) -> 500 | I17: =G17-H17 -> 0 | J17: 87000 | K17: =G17*J17 -> 43500000 | L17: =H17*J17 -> 43500000 | M17: =F17-TODAY() -> 185 | N17: =IF(M17<=0, "EXPIRED", IF(M17<=30, "EXPIRING SOON (<30 DAYS)", "SAFE")) -> SAFE | O17: =I17*J17 -> 0 | P17: =IF(OR(Q17="CRITICAL", Q17="EXPIRED"), O17, 0) -> 0 | Q17: =IF(M17<0, "EXPIRED", IF(M17<=60, "CRITICAL", IF(M17<=180, "WARNING", "SAFE"))) -> SAFE | R17: {=_xlfn.IFS(Q17="EXPIRED", "WRITE-OFF", Q17="WARNING", "FlASH SALE ", Q17="CRITICAL", "FEFO PRIORITY", Q17="SAFE", "REGULAR SALES")} -> REGULAR SALES
... A325: B2026-1320 | B325: TN-CEN-10 | C325: Centella Asiatica Soothing Essence | D325: Toner | E325: 46106 | F325: 46830 | G325: 250 | H325: =SUMIF(Analysis_FEFO!$E$5:$E$174, A325, Analysis_FEFO!$G$5:$G$174) -> 0 | I325: =G325-H325 -> 250 | J325: 58000 | K325: =G325*J325 -> 14500000 | L325: =H325*J325 -> 0 | M325: =F325-TODAY() -> 508 | N325: =IF(M325<=0, "EXPIRED", IF(M325<=30, "EXPIRING SOON (<30 DAYS)", "SAFE")) -> SAFE | O325: =I325*J325 -> 14500000 | P325: =IF(OR(Q325="CRITICAL", Q325="EXPIRED"), O325, 0) -> 0 | Q325: =IF(M325<0, "EXPIRED", IF(M325<=60, "CRITICAL", IF(M325<=180, "WARNING", "SAFE"))) -> SAFE | R325: {=_xlfn.IFS(Q325="EXPIRED", "WRITE-OFF", Q325="WARNING", "FlASH SALE ", Q325="CRITICAL", "FEFO PRIORITY", Q325="SAFE", "REGULAR SALES")} -> REGULAR SALES
A326: Total | G326: =SUM(G6:G325) -> 114800 | H326: =SUM(H1:H325) -> 36950 | I326: =SUM(I1:I325) -> 77850 | K326: =SUM(K6:K325) -> 6243600000 | L326: =SUM(L1:L325) -> 2033050000 | O326: =SUM(O6:O325) -> 4210550000 | P326: =SUM(P6:P325) -> 776450000

Sheet Inbound_Batch
A1: PT AURA NUSANTARA COSMETICS
A2: Master Data Inbound Batch Stock & FEFO Expiry Alert (~320 Batch)
A4: Batch_ID | B4: SKU_Code | C4: Product_Name | D4: Category | E4: Inbound_Date | F4: Expiry_Date | G4: Qty_Inbound | H4: Unit_Cost | I4: Value_Total | J4: Days_To_Expiry | K4: Alert_Status
A5: B2026-1001 | B5: SK-RET-07 | C5: Retinol Night Cream 30g | D5: Moisturizer | E5: 46079 | F5: 46452 | G5: 300 | H5: 84000 | I5: =G5*H5 -> 25200000 | J5: =F5-TODAY() -> 130 | K5: =IF(J5<0, "EXPIRED", IF(J5<=60, "CRITICAL", IF(J5<=180, "WARNING", "SAFE"))) -> WARNING
A6: B2026-1002 | B6: CL-C20-03 | C6: Vitamin C Cleanser 100ml | D6: Cleanser | E6: 46023 | F6: 46546 | G6: 250 | H6: 34000 | I6: =G6*H6 -> 8500000 | J6: =F6-TODAY() -> 224 | K6: =IF(J6<0, "EXPIRED", IF(J6<=60, "CRITICAL", IF(J6<=180, "WARNING", "SAFE"))) -> SAFE
A7: B2026-1003 | B7: MK-LIP-06 | C7: Velvet Lip Tint 4g | D7: Makeup | E7: 46066 | F7: 46440 | G7: 200 | H7: 35000 | I7: =G7*H7 -> 7000000 | J7: =F7-TODAY() -> 118 | K7: =IF(J7<0, "EXPIRED", IF(J7<=60, "CRITICAL", IF(J7<=180, "WARNING", "SAFE"))) -> WARNING
A8: B2026-1004 | B8: MO-HYA-05 | C8: Hyaluronic Acid Moisturizer 50g | D8: Moisturizer | E8: 45969 | F8: 46245 | G8: 100 | H8: 68000 | I8: =G8*H8 -> 6800000 | J8: =F8-TODAY() -> -77 | K8: =IF(J8<0, "EXPIRED", IF(J8<=60, "CRITICAL", IF(J8<=180, "WARNING", "SAFE"))) -> EXPIRED
A9: B2026-1005 | B9: SK-NNC-01 | C9: Niacinamide Serum 30ml | D9: Serum | E9: 45867 | F9: 46514 | G9: 1000 | H9: 51000 | I9: =G9*H9 -> 51000000 | J9: =F9-TODAY() -> 192 | K9: =IF(J9<0, "EXPIRED", IF(J9<=60, "CRITICAL", IF(J9<=180, "WARNING", "SAFE"))) -> SAFE
A10: B2026-1006 | B10: CL-C20-03 | C10: Vitamin C Cleanser 100ml | D10: Cleanser | E10: 45863 | F10: 46592 | G10: 100 | H10: 34000 | I10: =G10*H10 -> 3400000 | J10: =F10-TODAY() -> 270 | K10: =IF(J10<0, "EXPIRED", IF(J10<=60, "CRITICAL", IF(J10<=180, "WARNING", "SAFE"))) -> SAFE
A11: B2026-1007 | B11: SK-RET-07 | C11: Retinol Night Cream 30g | D11: Moisturizer | E11: 45829 | F11: 46466 | G11: 750 | H11: 86000 | I11: =G11*H11 -> 64500000 | J11: =F11-TODAY() -> 144 | K11: =IF(J11<0, "EXPIRED", IF(J11<=60, "CRITICAL", IF(J11<=180, "WARNING", "SAFE"))) -> WARNING
A12: B2026-1008 | B12: SK-SUN-02 | C12: Sunscreen SPF 50 PA+++ | D12: Sunscreen | E12: 46073 | F12: 46514 | G12: 300 | H12: 61000 | I12: =G12*H12 -> 18300000 | J12: =F12-TODAY() -> 192 | K12: =IF(J12<0, "EXPIRED", IF(J12<=60, "CRITICAL", IF(J12<=180, "WARNING", "SAFE"))) -> SAFE
A13: B2026-1009 | B13: CL-MCL-08 | C13: Micellar Water Cleanse 250ml | D13: Cleanser | E13: 45843 | F13: 46551 | G13: 200 | H13: 28000 | I13: =G13*H13 -> 5600000 | J13: =F13-TODAY() -> 229 | K13: =IF(J13<0, "EXPIRED", IF(J13<=60, "CRITICAL", IF(J13<=180, "WARNING", "SAFE"))) -> SAFE
A14: B2026-1010 | B14: SK-SUN-02 | C14: Sunscreen SPF 50 PA+++ | D14: Sunscreen | E14: 45862 | F14: 46593 | G14: 100 | H14: 56000 | I14: =G14*H14 -> 5600000 | J14: =F14-TODAY() -> 271 | K14: =IF(J14<0, "EXPIRED", IF(J14<=60, "CRITICAL", IF(J14<=180, "WARNING", "SAFE"))) -> SAFE
A15: B2026-1011 | B15: TN-CEN-10 | C15: Centella Asiatica Soothing Essence | D15: Toner | E15: 45852 | F15: 46586 | G15: 750 | H15: 59000 | I15: =G15*H15 -> 44250000 | J15: =F15-TODAY() -> 264 | K15: =IF(J15<0, "EXPIRED", IF(J15<=60, "CRITICAL", IF(J15<=180, "WARNING", "SAFE"))) -> SAFE
A16: B2026-1012 | B16: SK-RET-07 | C16: Retinol Night Cream 30g | D16: Moisturizer | E16: 46060 | F16: 46507 | G16: 500 | H16: 87000 | I16: =G16*H16 -> 43500000 | J16: =F16-TODAY() -> 185 | K16: =IF(J16<0, "EXPIRED", IF(J16<=60, "CRITICAL", IF(J16<=180, "WARNING", "SAFE"))) -> SAFE
... A324: B2026-1320 | B324: TN-CEN-10 | C324: Centella Asiatica Soothing Essence | D324: Toner | E324: 46106 | F324: 46830 | G324: 250 | H324: 58000 | I324: =G324*H324 -> 14500000 | J324: =F324-TODAY() -> 508 | K324: =IF(J324<0, "EXPIRED", IF(J324<=60, "CRITICAL", IF(J324<=180, "WARNING", "SAFE"))) -> SAFE
A325: Total | G325: =SUM(G5:G324) -> 114800 | I325: =SUM(I5:I324) -> 6243600000

Sheet Outbound_Orders
A1: PT AURA NUSANTARA COSMETICS
A2: Sales Order Outbound Demand
A4: Order_ID | B4: Tgl_Kirim | C4: SKU_Code | D4: Product_Name | E4: Category | F4: Qty_Outbound
A5: ORD-5001 | B5: 46037 | C5: MK-LIP-06 | D5: Velvet Lip Tint 4g | E5: Makeup | F5: 400
A6: ORD-5002 | B6: 46081 | C6: CL-MCL-08 | D6: Micellar Water Cleanse 250ml | E6: Cleanser | F6: 200
A7: ORD-5003 | B7: 46058 | C7: SK-RET-07 | D7: Retinol Night Cream 30g | E7: Moisturizer | F7: 600
A8: ORD-5004 | B8: 46122 | C8: MO-HYA-05 | D8: Hyaluronic Acid Moisturizer 50g | E8: Moisturizer | F8: 400
A9: ORD-5005 | B9: 46062 | C9: MK-CUS-09 | D9: Coverage Cushion Foundation | E9: Makeup | F9: 150
A10: ORD-5006 | B10: 46124 | C10: TN-CEN-10 | D10: Centella Asiatica Soothing Essence | E10: Toner | F10: 200
A11: ORD-5007 | B11: 46078 | C11: MK-CUS-09 | D11: Coverage Cushion Foundation | E11: Makeup | F11: 1000
A12: ORD-5008 | B12: 46116 | C12: CL-MCL-08 | D12: Micellar Water Cleanse 250ml | E12: Cleanser | F12: 150
A13: ORD-5009 | B13: 46073 | C13: TN-CEN-10 | D13: Centella Asiatica Soothing Essence | E13: Toner | F13: 400
A14: ORD-5010 | B14: 46060 | C14: SK-SUN-02 | D14: Sunscreen SPF 50 PA+++ | E14: Sunscreen | F14: 300
A15: ORD-5011 | B15: 46096 | C15: TN-AHA-04 | D15: AHA/BHA Exfoliating Toner 150ml | E15: Toner | F15: 800
A16: ORD-5012 | B16: 46125 | C16: TN-CEN-10 | D16: Centella Asiatica Soothing Essence | E16: Toner | F16: 200
... A84: ORD-5080 | B84: 46044 | C84: SK-SUN-02 | D84: Sunscreen SPF 50 PA+++ | E84: Sunscreen | F84: 500
A85: Total | F85: =SUM(F5:F84) -> 36950

Sheet Analysis_FEFO
A1: PT AURA NUSANTARA COSMETICS
A2: Hasil Alokasi FEFO & Valuasi HPP FIFO (Realized Demand)
A4: Order_ID | B4: Shipment_Date | C4: SKU_Code | D4: Product_Name | E4: Batch_ID | F4: Expiry_Date | G4: Qty_Outbound | H4: Unit_Cost | I4: Total_COGS_Outbound | J4: FEFO Check
A5: ORD-5001 | B5: 46037 | C5: MK-LIP-06 | D5: Velvet Lip Tint 4g | E5: B2026-1071 | F5: =_xlfn.XLOOKUP(E5, Inbound_Batch!$A$5:$A$324, Inbound_Batch!$F$5:$F$324,,0) -> 46357 | G5: 300 | H5: 29000 | I5: =G5*H5 -> 8700000 | J5: =IF(F5 <= _xlfn.MINIFS($F$5:$F$174, $C$5:$C$174, C5), "Compliant", "Non-Compliant") -> Compliant
A6: ORD-5001 | B6: 46037 | C6: MK-LIP-06 | D6: Velvet Lip Tint 4g | E6: B2026-1273 | F6: =_xlfn.XLOOKUP(E6, Inbound_Batch!$A$5:$A$324, Inbound_Batch!$F$5:$F$324,,0) -> 46727 | G6: 100 | H6: 30000 | I6: =G6*H6 -> 3000000 | J6: =IF(F6 <= _xlfn.MINIFS($F$5:$F$174, $C$5:$C$174, C6), "Compliant", "Non-Compliant") -> Non-Compliant
A7: ORD-5002 | B7: 46081 | C7: CL-MCL-08 | D7: Micellar Water Cleanse 250ml | E7: B2026-1177 | F7: =_xlfn.XLOOKUP(E7, Inbound_Batch!$A$5:$A$324, Inbound_Batch!$F$5:$F$324,,0) -> 45975 | G7: 200 | H7: 26000 | I7: =G7*H7 -> 5200000 | J7: =IF(F7 <= _xlfn.MINIFS($F$5:$F$174, $C$5:$C$174, C7), "Compliant", "Non-Compliant") -> Compliant
A8: ORD-5003 | B8: 46058 | C8: SK-RET-07 | D8: Retinol Night Cream 30g | E8: B2026-1181 | F8: =_xlfn.XLOOKUP(E8, Inbound_Batch!$A$5:$A$324, Inbound_Batch!$F$5:$F$324,,0) -> 45913 | G8: 200 | H8: 81000 | I8: =G8*H8 -> 16200000 | J8: =IF(F8 <= _xlfn.MINIFS($F$5:$F$174, $C$5:$C$174, C8), "Compliant", "Non-Compliant") -> Compliant
A9: ORD-5003 | B9: 46058 | C9: SK-RET-07 | D9: Retinol Night Cream 30g | E9: B2026-1007 | F9: =_xlfn.XLOOKUP(E9, Inbound_Batch!$A$5:$A$324, Inbound_Batch!$F$5:$F$324,,0) -> 46466 | G9: 400 | H9: 86000 | I9: =G9*H9 -> 34400000 | J9: =IF(F9 <= _xlfn.MINIFS($F$5:$F$174, $C$5:$C$174, C9), "Compliant", "Non-Compliant") -> Non-Compliant
A10: ORD-5004 | B10: 46122 | C10: MO-HYA-05 | D10: Hyaluronic Acid Moisturizer 50g | E10: B2026-1132 | F10: =_xlfn.XLOOKUP(E10, Inbound_Batch!$A$5:$A$324, Inbound_Batch!$F$5:$F$324,,0) -> 46665 | G10: 400 | H10: 65000 | I10: =G10*H10 -> 26000000 | J10: =IF(F10 <= _xlfn.MINIFS($F$5:$F$174, $C$5:$C$174, C10), "Compliant", "Non-Compliant") -> Non-Compliant
A11: ORD-5005 | B11: 46062 | C11: MK-CUS-09 | D11: Coverage Cushion Foundation | E11: B2026-1264 | F11: =_xlfn.XLOOKUP(E11, Inbound_Batch!$A$5:$A$324, Inbound_Batch!$F$5:$F$324,,0) -> 46734 | G11: 150 | H11: 96000 | I11: =G11*H11 -> 14400000 | J11: =IF(F11 <= _xlfn.MINIFS($F$5:$F$174, $C$5:$C$174, C11), "Compliant", "Non-Compliant") -> Non-Compliant
A12: ORD-5006 | B12: 46124 | C12: TN-CEN-10 | D12: Centella Asiatica Soothing Essence | E12: B2026-1209 | F12: =_xlfn.XLOOKUP(E12, Inbound_Batch!$A$5:$A$324, Inbound_Batch!$F$5:$F$324,,0) -> 47014 | G12: 200 | H12: 52000 | I12: =G12*H12 -> 10400000 | J12: =IF(F12 <= _xlfn.MINIFS($F$5:$F$174, $C$5:$C$174, C12), "Compliant", "Non-Compliant") -> Non-Compliant
A13: ORD-5007 | B13: 46078 | C13: MK-CUS-09 | D13: Coverage Cushion Foundation | E13: B2026-1264 | F13: =_xlfn.XLOOKUP(E13, Inbound_Batch!$A$5:$A$324, Inbound_Batch!$F$5:$F$324,,0) -> 46734 | G13: 100 | H13: 96000 | I13: =G13*H13 -> 9600000 | J13: =IF(F13 <= _xlfn.MINIFS($F$5:$F$174, $C$5:$C$174, C13), "Compliant", "Non-Compliant") -> Non-Compliant
A14: ORD-5007 | B14: 46078 | C14: MK-CUS-09 | D14: Coverage Cushion Foundation | E14: B2026-1287 | F14: =_xlfn.XLOOKUP(E14, Inbound_Batch!$A$5:$A$324, Inbound_Batch!$F$5:$F$324,,0) -> 46370 | G14: 100 | H14: 85000 | I14: =G14*H14 -> 8500000 | J14: =IF(F14 <= _xlfn.MINIFS($F$5:$F$174, $C$5:$C$174, C14), "Compliant", "Non-Compliant") -> Compliant
A15: ORD-5007 | B15: 46078 | C15: MK-CUS-09 | D15: Coverage Cushion Foundation | E15: B2026-1256 | F15: =_xlfn.XLOOKUP(E15, Inbound_Batch!$A$5:$A$324, Inbound_Batch!$F$5:$F$324,,0) -> 46460 | G15: 500 | H15: 98000 | I15: =G15*H15 -> 49000000 | J15: =IF(F15 <= _xlfn.MINIFS($F$5:$F$174, $C$5:$C$174, C15), "Compliant", "Non-Compliant") -> Non-Compliant
A16: ORD-5007 | B16: 46078 | C16: MK-CUS-09 | D16: Coverage Cushion Foundation | E16: B2026-1121 | F16: =_xlfn.XLOOKUP(E16, Inbound_Batch!$A$5:$A$324, Inbound_Batch!$F$5:$F$324,,0) -> 46469 | G16: 200 | H16: 92000 | I16: =G16*H16 -> 18400000 | J16: =IF(F16 <= _xlfn.MINIFS($F$5:$F$174, $C$5:$C$174, C16), "Compliant", "Non-Compliant") -> Non-Compliant
... A174: ORD-5080 | B174: 46044 | C174: SK-SUN-02 | D174: Sunscreen SPF 50 PA+++ | E174: B2026-1088 | F174: =_xlfn.XLOOKUP(E174, Inbound_Batch!$A$5:$A$324, Inbound_Batch!$F$5:$F$324,,0) -> 46922 | G174: 100 | H174: 55000 | I174: =G174*H174 -> 5500000 | J174: =IF(F174 <= _xlfn.MINIFS($F$5:$F$174, $C$5:$C$174, C174), "Compliant", "Non-Compliant") -> Non-Compliant
A175: Total HPP Outbound | G175: =SUM(G5:G174) -> 36950 | I175: =SUM(I5:I174) -> 2033050000

Sheet PIVOT
A1: PT AURA NUSANTARA COSMETICS
A3: Stock Inbound, Outbound & Balance Summary
A5: Category | B5: Quantity Outbound | C5: Quantity Inbound | D5: Quantity Remaining
A6: Cleanser | B6: 5800 | C6: 23600 | D6: 17800
A7: Makeup | B7: 11650 | C7: 22250 | D7: 10600
A8: Moisturizer | B8: 6800 | C8: 21600 | D8: 14800
A9: Serum | B9: 2200 | C9: 13000 | D9: 10800
A10: Sunscreen | B10: 3700 | C10: 10700 | D10: 7000
A11: Toner | B11: 6800 | C11: 23650 | D11: 16850
A12: Grand Total | B12: 36950 | C12: 114800 | D12: 77850
A14: Inventory Quantity Distribution by Risk Status | K14: Expiry_Alert_30Days | L14: EXPIRING SOON (<30 DAYS)
A16: Alert_Status | B16: Quantity Remaining | D16: Alert_Status | E16: Ending Inventory Value | K16: Product_Name | L16: Days To Expiry
A17: CRITICAL | B17: 9250 | D17: CRITICAL | E17: 539850000 | K17: Retinol Night Cream 30g | L17: 29
A18: EXPIRED | B18: 5050 | D18: EXPIRED | E18: 236600000 | K18: Vitamin C Cleanser 100ml | L18: 29
A19: SAFE | B19: 48650 | D19: SAFE | E19: 2623500000 | K19: Hyaluronic Acid Moisturizer 50g | L19: 28
A20: WARNING | B20: 14900 | D20: WARNING | E20: 810600000 | K20: AHA/BHA Exfoliating Toner 150ml | L20: 9
A21: Grand Total | B21: 77850 | D21: Grand Total | E21: 4210550000 | K21: Coverage Cushion Foundation | L21: 5
K22: Centella Asiatica Soothing Essence | L22: 5
A23: FEFO, Flash Sale & Write-Off Distribution Matrix | K23: Velvet Lip Tint 4g | L23: 1
A25: Qty Remaining | B25: Category
A26: Action_Recommendation | B26: Cleanser | C26: Makeup | D26: Moisturizer | E26: Serum | F26: Sunscreen | G26: Toner
A27: FEFO PRIORITY | B27: 1300 | C27: 1800 | D27: 1100 | E27: 700 | F27: 1850 | G27: 2500
A28: FlASH SALE | B28: 2400 | C28: 1800 | D28: 3500 | E28: 1000 | F28: 1600 | G28: 4600
A29: REGULAR SALES | B29: 12100 | C29: 6550 | D29: 9900 | E29: 8300 | F29: 3350 | G29: 8450
A30: WRITE-OFF | B30: 2000 | C30: 450 | D30: 300 | E30: 800 | F30: 200 | G30: 1300
A33: Top 5 Products by Financial Risk Exposure
A35: Alert_Status | B35: (Multiple Items)
A37: Product_Name | B37: Risk Valuation
A38: Coverage Cushion Foundation | B38: 138750000
A39: Centella Asiatica Soothing Essence | B39: 133750000
A40: Sunscreen SPF 50 PA+++ | B40: 120250000
A41: AHA/BHA Exfoliating Toner 150ml | B41: 74200000
A42: Niacinamide Serum 30ml | B42: 73400000
A44: Top 5 Products by Ending Inventory Value
A46: Product_Name | B46: Ending Inventory Value
A47: Centella Asiatica Soothing Essence | B47: 680600000
A48: Retinol Night Cream 30g | B48: 680300000
A49: Niacinamide Serum 30ml | B49: 527050000
A50: Coverage Cushion Foundation | B50: 478950000
A51: Vitamin C Cleanser 100ml | B51: 438900000
